eyai/__init__.py
eyai/assistant.py
eyai-1.0.5.dist-info/METADATA
eyai-1.0.5.dist-info/WHEEL
eyai-1.0.5.dist-info/licenses/LICENSE
eyai-1.0.5.dist-info/RECORD
