Metadata-Version: 2.4
Name: eyai
Version: 1.0.5
Summary: A simple and intuitive wrapper around OpenAI Compatible APIs with tool support
Project-URL: Homepage, https://github.com/AvicennaJr/eyai
Project-URL: Repository, https://github.com/AvicennaJr/eyai
Project-URL: Documentation, https://github.com/AvicennaJr/eyai#readme
Project-URL: Bug Tracker, https://github.com/AvicennaJr/eyai/issues
Author-email: Fuad Habib <info@fuadhabib.xyz>
License-Expression: MIT
License-File: LICENSE
Keywords: ai,assistant,chatgpt,deepseek,function-calling,groq,llm,openai,tools
Classifier: Development Status :: 4 - Beta
Classifier: Intended Audience :: Developers
Classifier: License :: OSI Approved :: MIT License
Classifier: Operating System :: OS Independent
Classifier: Programming Language :: Python :: 3.8
Classifier: Programming Language :: Python :: 3.9
Classifier: Programming Language :: Python :: 3.10
Classifier: Programming Language :: Python :: 3.11
Classifier: Programming Language :: Python :: 3.12
Classifier: Topic :: Scientific/Engineering :: Artificial Intelligence
Classifier: Topic :: Software Development :: Libraries :: Python Modules
Classifier: Typing :: Typed
Requires-Python: >=3.8
Requires-Dist: openai>=1.0.0
Requires-Dist: typing-extensions>=4.0.0
Provides-Extra: dev
Requires-Dist: black>=23.0.0; extra == 'dev'
Requires-Dist: mypy>=1.0.0; extra == 'dev'
Requires-Dist: ruff>=0.1.0; extra == 'dev'
Requires-Dist: types-requests; extra == 'dev'
